maml/__init__.py
maml/encoder.py
maml/exceptions.py
maml/lexer.py
maml/parser.py
maml/py.typed
maml_py-0.1.1.dist-info/licenses/LICENSE
maml_py-0.1.1.dist-info/METADATA
maml_py-0.1.1.dist-info/WHEEL
maml_py-0.1.1.dist-info/top_level.txt
maml_py-0.1.1.dist-info/RECORD
