Metadata-Version: 2.4
Name: maml-py
Version: 0.1.1
Summary: A pure Python parser for MAML (Minimal Abstract Markup Language)
Author: Mathew Duggan
License-Expression: MIT
Project-URL: Homepage, https://gitlab.com/matdevdug/maml-py
Project-URL: Repository, https://gitlab.com/matdevdug/maml-py
Keywords: maml,parser,config,configuration
Classifier: Development Status :: 4 - Beta
Classifier: Intended Audience :: Developers
Classifier: Programming Language :: Python :: 3
Classifier: Programming Language :: Python :: 3.8
Classifier: Programming Language :: Python :: 3.9
Classifier: Programming Language :: Python :: 3.10
Classifier: Programming Language :: Python :: 3.11
Classifier: Programming Language :: Python :: 3.12
Classifier: Programming Language :: Python :: 3.13
Classifier: Topic :: Software Development :: Libraries :: Python Modules
Requires-Python: >=3.8
License-File: LICENSE
Dynamic: license-file
